pylcs_rs-0.1.2.dist-info/METADATA
pylcs_rs-0.1.2.dist-info/WHEEL
pylcs_rs-0.1.2.dist-info/licenses/LICENSE
pylcs_rs/__init__.py
pylcs_rs/pylcs_rs.cpython-313t-i386-linux-gnu.so
pylcs_rs-0.1.2.dist-info/RECORD
