Metadata-Version: 2.4
Name: pylcs-rs
Version: 0.1.2
Classifier: Programming Language :: Rust
Classifier: Programming Language :: Python :: 3.11
Classifier: Programming Language :: Python :: 3.12
License-File: LICENSE
Summary: Fast LCS algorithms implemented in Rust
Author-email: Kazuki Inamura <kzinmr109@gmail.com>
Requires-Python: >=3.8
